{
  "required": true,
  "minVersion": "0.8",
  "package": "net.borisshoes.ancestralarchetypes.mixins",
  "compatibilityLevel": "JAVA_21",
  "mixins": [
    "AbstractHorseDonkeyMixin",
    "AbstractHorseMixin",
    "CreeperMixin",
    "EntityAccessor",
    "EntityMixin",
    "FallingBlockEntityAccessor",
    "FarmlandBlockMixin",
    "FeastingCharmItemMixin",
    "ItemEntityMixin",
    "ItemMixin",
    "ItemStackMixin",
    "LivingEntityAccessor",
    "LivingEntityMixin",
    "PhantomSpawnerMixin",
    "PhantomSwoopGoalMixin",
    "PlayerEntityMixin",
    "PolymerBlockUtilsMixin",
    "PowderSnowBlockMixin",
    "ServerPlayerEntityMixin",
    "ServerPlayerInteractionManagerMixin",
    "ServerPlayNetworkHandlerMixin",
    "SnowballEntityMixin",
    "ThrownItemEntityAccessor"
  ],
  "client": [
  ],
  "injectors": {
    "defaultRequire": 1
  }
}
